{
  "exceptions": [
    {
      "key": "ילו",
      "category": "דלק וחניה",
      "reason": "המפתח מוכל בתוך \"איילון\" (ביטוח) הקיים — עלול לחטוף אותו"
    },
    {
      "key": "sogood",
      "category": "דלק וחניה",
      "reason": "קיים כבר במאגר עם קטגוריה אחרת: \"סיגריות\" — מיזוג ידרוס את הקיים | המפתח מוכל בתוך \"sogood\" (סיגריות) הקיים — עלול לחטוף אותו"
    },
    {
      "key": "מיקה",
      "category": "דלק וחניה",
      "reason": "המפתח מוכל בתוך \"מיקה גז\" (הוצאות בית) הקיים — עלול לחטוף אותו"
    },
    {
      "key": "זברה",
      "category": "תיקוני רכב",
      "reason": "קיים כבר במאגר עם קטגוריה אחרת: \"ביגוד והנעלה\" — מיזוג ידרוס את הקיים"
    }
  ],
  "rejected": [],
  "warnings": [
    {
      "key": "אלקטרה פאוור",
      "category": "דלק וחניה",
      "reason": "מכיל את \"קטר\" (ריהוט והבית) הקיים — בטוח: הארוך מנצח"
    },
    {
      "key": "electra power",
      "category": "דלק וחניה",
      "reason": "מכיל את \"electra\" (כלי בית) הקיים — בטוח: הארוך מנצח"
    }
  ]
}