{
  "exceptions": [
    {
      "key": "כפר השעשועים",
      "category": "צעצועים",
      "reason": "קיים כבר במאגר עם קטגוריה אחרת: \"תחביבים\" — מיזוג ידרוס את הקיים | המפתח מוכל בתוך \"כפר השעשועים\" (תחביבים) הקיים — עלול לחטוף אותו"
    },
    {
      "key": "הפיראט האדום",
      "category": "צעצועים",
      "reason": "קיים כבר במאגר עם קטגוריה אחרת: \"תחביבים\" — מיזוג ידרוס את הקיים | המפתח מוכל בתוך \"הפיראט האדום\" (תחביבים) הקיים — עלול לחטוף אותו"
    },
    {
      "key": "פעלטון",
      "category": "חינוך וקייטנות",
      "reason": "קיים כבר במאגר עם קטגוריה אחרת: \"תחביבים\" — מיזוג ידרוס את הקיים | המפתח מוכל בתוך \"פעלטון\" (תחביבים) הקיים — עלול לחטוף אותו"
    },
    {
      "key": "איי ג'אמפ",
      "category": "חינוך וקייטנות",
      "reason": "קיים כבר במאגר עם קטגוריה אחרת: \"תחביבים\" — מיזוג ידרוס את הקיים | המפתח מוכל בתוך \"איי ג'אמפ\" (תחביבים) הקיים — עלול לחטוף אותו"
    },
    {
      "key": "ijump",
      "category": "חינוך וקייטנות",
      "reason": "קיים כבר במאגר עם קטגוריה אחרת: \"תחביבים\" — מיזוג ידרוס את הקיים | המפתח מוכל בתוך \"ijump\" (תחביבים) הקיים — עלול לחטוף אותו"
    },
    {
      "key": "מדעטק",
      "category": "חינוך וקייטנות",
      "reason": "קיים כבר במאגר עם קטגוריה אחרת: \"תחביבים\" — מיזוג ידרוס את הקיים | המפתח מוכל בתוך \"מדעטק\" (תחביבים) הקיים — עלול לחטוף אותו"
    },
    {
      "key": "הרצליה מדיקל",
      "category": "בריאות",
      "reason": "המפתח משתנה בנרמול (\"מדיקל\") — כנראה מכיל שם עיר/בע\"מ; יש להזין את הצורה המנורמלת"
    },
    {
      "key": "אודיבל",
      "category": "מנויים",
      "reason": "קיים כבר במאגר עם קטגוריה אחרת: \"תחביבים\" — מיזוג ידרוס את הקיים | המפתח מוכל בתוך \"אודיבל\" (תחביבים) הקיים — עלול לחטוף אותו"
    },
    {
      "key": "מיניסו",
      "category": "מתנות",
      "reason": "קיים כבר במאגר עם קטגוריה אחרת: \"ריהוט והבית\" — מיזוג ידרוס את הקיים"
    },
    {
      "key": "miniso",
      "category": "מתנות",
      "reason": "קיים כבר במאגר עם קטגוריה אחרת: \"ריהוט והבית\" — מיזוג ידרוס את הקיים | המפתח מוכל בתוך \"miniso\" (ריהוט והבית) הקיים — עלול לחטוף אותו"
    },
    {
      "key": "קרביץ",
      "category": "ציוד עסקי/משרדי",
      "reason": "קיים כבר במאגר עם קטגוריה אחרת: \"תחביבים\" — מיזוג ידרוס את הקיים | המפתח מוכל בתוך \"קרביץ ישראל\" (תחביבים) הקיים — עלול לחטוף אותו"
    }
  ],
  "rejected": [],
  "warnings": [
    {
      "key": "petmarket",
      "category": "בעלי חיים",
      "reason": "מכיל את \"arket\" (ביגוד והנעלה) הקיים — בטוח: הארוך מנצח"
    },
    {
      "key": "פטמקס",
      "category": "בעלי חיים",
      "reason": "מכיל את \"מקס\" (עמלות בנק ואשראי) הקיים — בטוח: הארוך מנצח"
    },
    {
      "key": "vetmarket",
      "category": "בעלי חיים",
      "reason": "מכיל את \"arket\" (ביגוד והנעלה) הקיים — בטוח: הארוך מנצח"
    },
    {
      "key": "vet market",
      "category": "בעלי חיים",
      "reason": "מכיל את \"arket\" (ביגוד והנעלה) הקיים — בטוח: הארוך מנצח"
    },
    {
      "key": "idan2000",
      "category": "צעצועים",
      "reason": "מכיל את \"dan\" (תחבצ) הקיים — בטוח: הארוך מנצח"
    },
    {
      "key": "idan 2000",
      "category": "צעצועים",
      "reason": "מכיל את \"dan\" (תחבצ) הקיים — בטוח: הארוך מנצח"
    },
    {
      "key": "קידי טויס",
      "category": "צעצועים",
      "reason": "מכיל את \"יס\" (מנויים) הקיים — בטוח: הארוך מנצח"
    },
    {
      "key": "kiditoys",
      "category": "צעצועים",
      "reason": "מכיל את \"idi\" (ביטוח) הקיים — בטוח: הארוך מנצח"
    },
    {
      "key": "סייבר קידס",
      "category": "חינוך וקייטנות",
      "reason": "מכיל את \"בר\" (אוכל בחוץ ובילויים) הקיים — בטוח: הארוך מנצח"
    },
    {
      "key": "שחקים סייבר",
      "category": "חינוך וקייטנות",
      "reason": "מכיל את \"בר\" (אוכל בחוץ ובילויים) הקיים — בטוח: הארוך מנצח"
    },
    {
      "key": "סקיי ג'אמפ",
      "category": "חינוך וקייטנות",
      "reason": "מכיל את \"ג'אמפ\" (ביגוד והנעלה) הקיים — בטוח: הארוך מנצח"
    },
    {
      "key": "skyjump",
      "category": "חינוך וקייטנות",
      "reason": "מכיל את \"jump\" (ביגוד והנעלה) הקיים — בטוח: הארוך מנצח"
    },
    {
      "key": "sky jump",
      "category": "חינוך וקייטנות",
      "reason": "מכיל את \"jump\" (ביגוד והנעלה) הקיים — בטוח: הארוך מנצח"
    },
    {
      "key": "2jump",
      "category": "חינוך וקייטנות",
      "reason": "מכיל את \"jump\" (ביגוד והנעלה) הקיים — בטוח: הארוך מנצח"
    },
    {
      "key": "מוזיאון המדע",
      "category": "חינוך וקייטנות",
      "reason": "מכיל את \"מוזיאון\" (תחביבים) הקיים — בטוח: הארוך מנצח"
    },
    {
      "key": "מכבי טבעי",
      "category": "בריאות",
      "reason": "מכיל את \"מכבי\" (קופת חולים) הקיים — בטוח: הארוך מנצח"
    },
    {
      "key": "אמזון פריים",
      "category": "מנויים",
      "reason": "מכיל את \"אמזון\" (שונות) הקיים — בטוח: הארוך מנצח"
    },
    {
      "key": "סבון של פעם",
      "category": "מתנות",
      "reason": "מכיל את \"סבון\" (תספורת וקוסמטיקה) הקיים — בטוח: הארוך מנצח"
    },
    {
      "key": "אופיס דיפו",
      "category": "ציוד עסקי/משרדי",
      "reason": "מכיל את \"יס\" (מנויים) הקיים — בטוח: הארוך מנצח"
    },
    {
      "key": "office depot",
      "category": "ציוד עסקי/משרדי",
      "reason": "מכיל את \"depo\" (מזון לבית) הקיים — בטוח: הארוך מנצח"
    },
    {
      "key": "officedepot",
      "category": "ציוד עסקי/משרדי",
      "reason": "מכיל את \"depo\" (מזון לבית) הקיים — בטוח: הארוך מנצח"
    }
  ]
}